engineering_tool/__init__.py
engineering_tool/__version__.py
engineering_tool/areas.py
engineering_tool/electrics.py
engineering_tool/pressures.py
engineering_tool/temperatures.py
engineering_tool/units.py
engineering_tool/volumes.py
engineering_tool-0.0.2.dist-info/METADATA
engineering_tool-0.0.2.dist-info/RECORD
engineering_tool-0.0.2.dist-info/WHEEL
engineering_tool-0.0.2.dist-info/top_level.txt
